peeker.py
htmlpeeker-0.1.2.dist-info/DESCRIPTION.rst
htmlpeeker-0.1.2.dist-info/METADATA
htmlpeeker-0.1.2.dist-info/RECORD
htmlpeeker-0.1.2.dist-info/WHEEL
htmlpeeker-0.1.2.dist-info/metadata.json
htmlpeeker-0.1.2.dist-info/top_level.txt
