Metadata-Version: 2.0
Name: htmlpeeker
Version: 0.1.2
Summary: Peek html:)
Home-page: https://github.com/harukaeru/HTMLPeeker
Author: harukaeru
Author-email: nekoneko.myaomyao@gmail.com
License: MIT
Platform: UNKNOWN
